synthia/__init__.py
synthia/conftest.py
synthia/distribution.py
synthia/transform.py
synthia/util.py
synthia/copulas/__init__.py
synthia/copulas/copula.py
synthia/copulas/gaussian.py
synthia/copulas/independence.py
synthia/copulas/vine.py
synthia/generators/__init__.py
synthia/generators/copula.py
synthia/generators/fpca.py
synthia/parameterizers/__init__.py
synthia/parameterizers/const.py
synthia/parameterizers/distribution.py
synthia/parameterizers/parameterizer.py
synthia/parameterizers/quantile.py
synthia-1.1.0.dist-info/LICENSE.txt
synthia-1.1.0.dist-info/METADATA
synthia-1.1.0.dist-info/WHEEL
synthia-1.1.0.dist-info/top_level.txt
synthia-1.1.0.dist-info/RECORD
