Metadata-Version: 2.1
Name: synthia
Version: 1.1.0
Summary: Multidimensional synthetic data generation in Python
Home-page: https://github.com/dmey/synthia
Author: D. Meyer, T. Nagler
License: MIT
Platform: UNKNOWN
Classifier: Development Status :: 4 - Beta
Classifier: Intended Audience :: Science/Research
Classifier: Programming Language :: Python :: 3
Requires-Python: >=3.8
Requires-Dist: numpy
Requires-Dist: scipy
Requires-Dist: xarray
Requires-Dist: bottleneck
Provides-Extra: full
Requires-Dist: pyvinecopulib (==0.5.5) ; extra == 'full'
